r_cli/__init__.py
r_cli/main.py
r_cli/py.typed
r_cli/api/__init__.py
r_cli/api/audit.py
r_cli/api/auth.py
r_cli/api/models.py
r_cli/api/permissions.py
r_cli/api/rate_limit.py
r_cli/api/server.py
r_cli/backends/__init__.py
r_cli/backends/auto.py
r_cli/backends/base.py
r_cli/backends/mlx.py
r_cli/backends/ollama.py
r_cli/backends/openai_compat.py
r_cli/core/__init__.py
r_cli/core/agent.py
r_cli/core/config.py
r_cli/core/embeddings.py
r_cli/core/exceptions.py
r_cli/core/llm.py
r_cli/core/logging.py
r_cli/core/memory.py
r_cli/core/orchestrator.py
r_cli/core/plugins.py
r_cli/core/voice_interface.py
r_cli/skills/__init__.py
r_cli/skills/android_skill.py
r_cli/skills/archive_skill.py
r_cli/skills/audio_skill.py
r_cli/skills/barcode_skill.py
r_cli/skills/benchmark_skill.py
r_cli/skills/bluetooth_skill.py
r_cli/skills/calendar_skill.py
r_cli/skills/changelog_skill.py
r_cli/skills/clipboard_skill.py
r_cli/skills/code_skill.py
r_cli/skills/color_skill.py
r_cli/skills/cron_skill.py
r_cli/skills/crypto_skill.py
r_cli/skills/csv_skill.py
r_cli/skills/currency_skill.py
r_cli/skills/datetime_skill.py
r_cli/skills/design_skill.py
r_cli/skills/diff_skill.py
r_cli/skills/docker_skill.py
r_cli/skills/email_skill.py
r_cli/skills/encoding_skill.py
r_cli/skills/env_skill.py
r_cli/skills/faker_skill.py
r_cli/skills/fs_skill.py
r_cli/skills/git_skill.py
r_cli/skills/gpio_skill.py
r_cli/skills/html_skill.py
r_cli/skills/http_skill.py
r_cli/skills/hublab_skill.py
r_cli/skills/ical_skill.py
r_cli/skills/image_skill.py
r_cli/skills/ip_skill.py
r_cli/skills/json_skill.py
r_cli/skills/jwt_skill.py
r_cli/skills/latex_skill.py
r_cli/skills/logs_skill.py
r_cli/skills/manifest_skill.py
r_cli/skills/markdown_skill.py
r_cli/skills/math_skill.py
r_cli/skills/metrics_skill.py
r_cli/skills/mime_skill.py
r_cli/skills/multiagent_skill.py
r_cli/skills/network_skill.py
r_cli/skills/ocr_skill.py
r_cli/skills/openapi_skill.py
r_cli/skills/pdf_skill.py
r_cli/skills/pdftools_skill.py
r_cli/skills/plugin_skill.py
r_cli_ai-0.3.2.dist-info/METADATA
r_cli_ai-0.3.2.dist-info/WHEEL
r_cli_ai-0.3.2.dist-info/entry_points.txt
r_cli_ai-0.3.2.dist-info/licenses/LICENSE
r_cli_ai-0.3.2.dist-info/RECORD
