Metadata-Version: 2.4
Name: r-cli-ai
Version: 0.3.2
Summary: R CLI - Local AI Agent Runtime. Tool orchestrator connecting local LLMs to 74 system tools via function calling.
Project-URL: Homepage, https://github.com/raym33/r
Project-URL: Repository, https://github.com/raym33/r
Project-URL: Documentation, https://github.com/raym33/r#readme
Project-URL: Issues, https://github.com/raym33/r/issues
Author-email: Ramón Guillamón <learntouseai@gmail.com>
License: MIT
License-File: LICENSE
Keywords: agent,ai,cli,code-generation,llm,lm-studio,local,offline,ollama,pdf,private,productivity,rag,sql,voice,whisper
Classifier: Development Status :: 4 - Beta
Classifier: Environment :: Console
Classifier: Intended Audience :: Developers
Classifier: Intended Audience :: End Users/Desktop
Classifier: License :: OSI Approved :: MIT License
Classifier: Operating System :: OS Independent
Classifier: Programming Language :: Python :: 3
Classifier: Programming Language :: Python :: 3.10
Classifier: Programming Language :: Python :: 3.11
Classifier: Programming Language :: Python :: 3.12
Classifier: Topic :: Scientific/Engineering :: Artificial Intelligence
Classifier: Topic :: Utilities
Requires-Python: >=3.10
Requires-Dist: click>=8.0.0
Requires-Dist: duckdb>=0.9.0
Requires-Dist: fastapi>=0.109.0
Requires-Dist: fpdf2>=2.7.0
Requires-Dist: httpx>=0.25.0
Requires-Dist: jinja2>=3.0.0
Requires-Dist: openai>=1.0.0
Requires-Dist: pandas>=2.0.0
Requires-Dist: passlib[bcrypt]>=1.7.0
Requires-Dist: pillow>=10.0.0
Requires-Dist: pydantic>=2.0.0
Requires-Dist: pypdf>=3.0.0
Requires-Dist: python-docx>=1.0.0
Requires-Dist: python-jose[cryptography]>=3.3.0
Requires-Dist: pyyaml>=6.0.0
Requires-Dist: requests>=2.31.0
Requires-Dist: rich>=13.0.0
Requires-Dist: tiktoken>=0.5.0
Requires-Dist: uvicorn[standard]>=0.27.0
Provides-Extra: all
Requires-Dist: accelerate>=0.25.0; extra == 'all'
Requires-Dist: beautifulsoup4>=4.12.0; extra == 'all'
Requires-Dist: chromadb>=0.4.0; extra == 'all'
Requires-Dist: deep-translator>=1.11.0; extra == 'all'
Requires-Dist: diffusers>=0.25.0; extra == 'all'
Requires-Dist: faster-whisper>=0.10.0; extra == 'all'
Requires-Dist: jmespath>=1.0.0; extra == 'all'
Requires-Dist: jsonschema>=4.0.0; extra == 'all'
Requires-Dist: langdetect>=1.0.9; extra == 'all'
Requires-Dist: lxml>=4.9.0; extra == 'all'
Requires-Dist: numpy>=1.24.0; extra == 'all'
Requires-Dist: piper-tts>=1.0.0; extra == 'all'
Requires-Dist: psycopg2-binary>=2.9.0; extra == 'all'
Requires-Dist: pytesseract>=0.3.10; extra == 'all'
Requires-Dist: sentence-transformers>=2.2.0; extra == 'all'
Requires-Dist: textual>=0.47.0; extra == 'all'
Requires-Dist: torch>=2.0.0; extra == 'all'
Provides-Extra: all-mac
Requires-Dist: accelerate>=0.25.0; extra == 'all-mac'
Requires-Dist: beautifulsoup4>=4.12.0; extra == 'all-mac'
Requires-Dist: chromadb>=0.4.0; extra == 'all-mac'
Requires-Dist: deep-translator>=1.11.0; extra == 'all-mac'
Requires-Dist: diffusers>=0.25.0; extra == 'all-mac'
Requires-Dist: faster-whisper>=0.10.0; extra == 'all-mac'
Requires-Dist: huggingface-hub>=0.20.0; extra == 'all-mac'
Requires-Dist: jmespath>=1.0.0; extra == 'all-mac'
Requires-Dist: jsonschema>=4.0.0; extra == 'all-mac'
Requires-Dist: langdetect>=1.0.9; extra == 'all-mac'
Requires-Dist: lxml>=4.9.0; extra == 'all-mac'
Requires-Dist: mlx-lm>=0.10.0; extra == 'all-mac'
Requires-Dist: numpy>=1.24.0; extra == 'all-mac'
Requires-Dist: piper-tts>=1.0.0; extra == 'all-mac'
Requires-Dist: psycopg2-binary>=2.9.0; extra == 'all-mac'
Requires-Dist: pytesseract>=0.3.10; extra == 'all-mac'
Requires-Dist: sentence-transformers>=2.2.0; extra == 'all-mac'
Requires-Dist: textual>=0.47.0; extra == 'all-mac'
Requires-Dist: torch>=2.0.0; extra == 'all-mac'
Provides-Extra: all-rpi
Requires-Dist: accelerate>=0.25.0; extra == 'all-rpi'
Requires-Dist: beautifulsoup4>=4.12.0; extra == 'all-rpi'
Requires-Dist: chromadb>=0.4.0; extra == 'all-rpi'
Requires-Dist: deep-translator>=1.11.0; extra == 'all-rpi'
Requires-Dist: diffusers>=0.25.0; extra == 'all-rpi'
Requires-Dist: faster-whisper>=0.10.0; extra == 'all-rpi'
Requires-Dist: gpiozero>=2.0.0; extra == 'all-rpi'
Requires-Dist: jmespath>=1.0.0; extra == 'all-rpi'
Requires-Dist: jsonschema>=4.0.0; extra == 'all-rpi'
Requires-Dist: langdetect>=1.0.9; extra == 'all-rpi'
Requires-Dist: lxml>=4.9.0; extra == 'all-rpi'
Requires-Dist: numpy>=1.24.0; extra == 'all-rpi'
Requires-Dist: piper-tts>=1.0.0; extra == 'all-rpi'
Requires-Dist: psycopg2-binary>=2.9.0; extra == 'all-rpi'
Requires-Dist: pytesseract>=0.3.10; extra == 'all-rpi'
Requires-Dist: rpi-gpio>=0.7.0; extra == 'all-rpi'
Requires-Dist: sentence-transformers>=2.2.0; extra == 'all-rpi'
Requires-Dist: textual>=0.47.0; extra == 'all-rpi'
Requires-Dist: torch>=2.0.0; extra == 'all-rpi'
Provides-Extra: audio
Requires-Dist: faster-whisper>=0.10.0; extra == 'audio'
Requires-Dist: piper-tts>=1.0.0; extra == 'audio'
Provides-Extra: design
Requires-Dist: accelerate>=0.25.0; extra == 'design'
Requires-Dist: diffusers>=0.25.0; extra == 'design'
Requires-Dist: torch>=2.0.0; extra == 'design'
Provides-Extra: dev
Requires-Dist: build>=1.0.0; extra == 'dev'
Requires-Dist: pytest-asyncio>=0.21.0; extra == 'dev'
Requires-Dist: pytest>=7.0.0; extra == 'dev'
Requires-Dist: ruff>=0.1.0; extra == 'dev'
Requires-Dist: twine>=4.0.0; extra == 'dev'
Provides-Extra: json-tools
Requires-Dist: jmespath>=1.0.0; extra == 'json-tools'
Requires-Dist: jsonschema>=4.0.0; extra == 'json-tools'
Provides-Extra: mlx
Requires-Dist: huggingface-hub>=0.20.0; extra == 'mlx'
Requires-Dist: mlx-lm>=0.10.0; extra == 'mlx'
Provides-Extra: ocr
Requires-Dist: pytesseract>=0.3.10; extra == 'ocr'
Provides-Extra: postgres
Requires-Dist: psycopg2-binary>=2.9.0; extra == 'postgres'
Provides-Extra: rag
Requires-Dist: chromadb>=0.4.0; extra == 'rag'
Requires-Dist: numpy>=1.24.0; extra == 'rag'
Requires-Dist: sentence-transformers>=2.2.0; extra == 'rag'
Provides-Extra: rpi
Requires-Dist: gpiozero>=2.0.0; extra == 'rpi'
Requires-Dist: rpi-gpio>=0.7.0; extra == 'rpi'
Provides-Extra: simulator
Requires-Dist: textual>=0.47.0; extra == 'simulator'
Provides-Extra: translate
Requires-Dist: deep-translator>=1.11.0; extra == 'translate'
Requires-Dist: langdetect>=1.0.9; extra == 'translate'
Provides-Extra: web
Requires-Dist: beautifulsoup4>=4.12.0; extra == 'web'
Requires-Dist: lxml>=4.9.0; extra == 'web'
